{
  "data_list": [
    {
      "group_id": 1699135692,
      "reward_parcel_type": 2,
      "reward_parcel_id": 1,
      "reward_parcel_amount": 1400,
      "reward_parcel_probability": 1000,
      "is_displayed": true,
      "drop_item_model_prefab_path": "Effect/Common/FX_Common_DropItem_Yellow"
    },
    {
      "group_id": 1699135692,
      "reward_parcel_type": 2,
      "reward_parcel_id": 1,
      "reward_parcel_amount": 1000,
      "reward_parcel_probability": 5000,
      "is_displayed": true,
      "drop_item_model_prefab_path": "Effect/Common/FX_Common_DropItem_Purple"
    },
    {
      "group_id": 1699135692,
      "reward_parcel_type": 2,
      "reward_parcel_id": 1,
      "reward_parcel_amount": 900,
      "reward_parcel_probability": 4000,
      "is_displayed": true,
      "drop_item_model_prefab_path": "Effect/Common/FX_Common_DropItem_Blue"
    },
    {
      "group_id": 3485155052,
      "reward_parcel_type": 2,
      "reward_parcel_id": 1,
      "reward_parcel_amount": 3760,
      "reward_parcel_probability": 1000,
      "is_displayed": true,
      "drop_item_model_prefab_path": "Effect/Common/FX_Common_DropItem_Yellow"
    },
    {
      "group_id": 3485155052,
      "reward_parcel_type": 2,
      "reward_parcel_id": 1,
      "reward_parcel_amount": 2680,
      "reward_parcel_probability": 5000,
      "is_displayed": true,
      "drop_item_model_prefab_path": "Effect/Common/FX_Common_DropItem_Purple"
    },
    {
      "group_id": 3485155052,
      "reward_parcel_type": 2,
      "reward_parcel_id": 1,
      "reward_parcel_amount": 1710,
      "reward_parcel_probability": 4000,
      "is_displayed": true,
      "drop_item_model_prefab_path": "Effect/Common/FX_Common_DropItem_Blue"
    },
    {
      "group_id": 1688928395,
      "reward_parcel_type": 2,
      "reward_parcel_id": 1,
      "reward_parcel_amount": 6000,
      "reward_parcel_probability": 1000,
      "is_displayed": true,
      "drop_item_model_prefab_path": "Effect/Common/FX_Common_DropItem_Yellow"
    },
    {
      "group_id": 1688928395,
      "reward_parcel_type": 2,
      "reward_parcel_id": 1,
      "reward_parcel_amount": 4800,
      "reward_parcel_probability": 5000,
      "is_displayed": true,
      "drop_item_model_prefab_path": "Effect/Common/FX_Common_DropItem_Purple"
    },
    {
      "group_id": 1688928395,
      "reward_parcel_type": 2,
      "reward_parcel_id": 1,
      "reward_parcel_amount": 3000,
      "reward_parcel_probability": 4000,
      "is_displayed": true,
      "drop_item_model_prefab_path": "Effect/Common/FX_Common_DropItem_Blue"
    },
    {
      "group_id": 21190413,
      "reward_parcel_type": 2,
      "reward_parcel_id": 1,
      "reward_parcel_amount": 10330,
      "reward_parcel_probability": 1000,
      "is_displayed": true,
      "drop_item_model_prefab_path": "Effect/Common/FX_Common_DropItem_Yellow"
    },
    {
      "group_id": 21190413,
      "reward_parcel_type": 2,
      "reward_parcel_id": 1,
      "reward_parcel_amount": 6750,
      "reward_parcel_probability": 5000,
      "is_displayed": true,
      "drop_item_model_prefab_path": "Effect/Common/FX_Common_DropItem_Purple"
    },
    {
      "group_id": 21190413,
      "reward_parcel_type": 2,
      "reward_parcel_id": 1,
      "reward_parcel_amount": 4980,
      "reward_parcel_probability": 4000,
      "is_displayed": true,
      "drop_item_model_prefab_path": "Effect/Common/FX_Common_DropItem_Blue"
    },
    {
      "group_id": 29510467,
      "reward_parcel_type": 2,
      "reward_parcel_id": 1,
      "reward_parcel_amount": 13980,
      "reward_parcel_probability": 1000,
      "is_displayed": true,
      "drop_item_model_prefab_path": "Effect/Common/FX_Common_DropItem_Yellow"
    },
    {
      "group_id": 29510467,
      "reward_parcel_type": 2,
      "reward_parcel_id": 1,
      "reward_parcel_amount": 9860,
      "reward_parcel_probability": 5000,
      "is_displayed": true,
      "drop_item_model_prefab_path": "Effect/Common/FX_Common_DropItem_Purple"
    },
    {
      "group_id": 29510467,
      "reward_parcel_type": 2,
      "reward_parcel_id": 1,
      "reward_parcel_amount": 6680,
      "reward_parcel_probability": 4000,
      "is_displayed": true,
      "drop_item_model_prefab_path": "Effect/Common/FX_Common_DropItem_Blue"
    },
    {
      "group_id": 3610473423,
      "reward_parcel_type": 2,
      "reward_parcel_id": 1,
      "reward_parcel_amount": 18300,
      "reward_parcel_probability": 1000,
      "is_displayed": true,
      "drop_item_model_prefab_path": "Effect/Common/FX_Common_DropItem_Yellow"
    },
    {
      "group_id": 3610473423,
      "reward_parcel_type": 2,
      "reward_parcel_id": 1,
      "reward_parcel_amount": 13140,
      "reward_parcel_probability": 5000,
      "is_displayed": true,
      "drop_item_model_prefab_path": "Effect/Common/FX_Common_DropItem_Purple"
    },
    {
      "group_id": 3610473423,
      "reward_parcel_type": 2,
      "reward_parcel_id": 1,
      "reward_parcel_amount": 9000,
      "reward_parcel_probability": 4000,
      "is_displayed": true,
      "drop_item_model_prefab_path": "Effect/Common/FX_Common_DropItem_Blue"
    },
    {
      "group_id": 1372438453,
      "reward_parcel_type": 2,
      "reward_parcel_id": 1,
      "reward_parcel_amount": 21260,
      "reward_parcel_probability": 1000,
      "is_displayed": true,
      "drop_item_model_prefab_path": "Effect/Common/FX_Common_DropItem_Yellow"
    },
    {
      "group_id": 1372438453,
      "reward_parcel_type": 2,
      "reward_parcel_id": 1,
      "reward_parcel_amount": 17380,
      "reward_parcel_probability": 5000,
      "is_displayed": true,
      "drop_item_model_prefab_path": "Effect/Common/FX_Common_DropItem_Purple"
    },
    {
      "group_id": 1372438453,
      "reward_parcel_type": 2,
      "reward_parcel_id": 1,
      "reward_parcel_amount": 11460,
      "reward_parcel_probability": 4000,
      "is_displayed": true,
      "drop_item_model_prefab_path": "Effect/Common/FX_Common_DropItem_Blue"
    },
    {
      "group_id": 2587047723,
      "reward_parcel_type": 2,
      "reward_parcel_id": 1,
      "reward_parcel_amount": 30100,
      "reward_parcel_probability": 1000,
      "is_displayed": true,
      "drop_item_model_prefab_path": "Effect/Common/FX_Common_DropItem_Yellow"
    },
    {
      "group_id": 2587047723,
      "reward_parcel_type": 2,
      "reward_parcel_id": 1,
      "reward_parcel_amount": 20300,
      "reward_parcel_probability": 5000,
      "is_displayed": true,
      "drop_item_model_prefab_path": "Effect/Common/FX_Common_DropItem_Purple"
    },
    {
      "group_id": 2587047723,
      "reward_parcel_type": 2,
      "reward_parcel_id": 1,
      "reward_parcel_amount": 15100,
      "reward_parcel_probability": 4000,
      "is_displayed": true,
      "drop_item_model_prefab_path": "Effect/Common/FX_Common_DropItem_Blue"
    },
    {
      "group_id": 2271403252,
      "reward_parcel_type": 2,
      "reward_parcel_id": 1,
      "reward_parcel_amount": 32600,
      "reward_parcel_probability": 1000,
      "is_displayed": true,
      "drop_item_model_prefab_path": "Effect/Common/FX_Common_DropItem_Yellow"
    },
    {
      "group_id": 2271403252,
      "reward_parcel_type": 2,
      "reward_parcel_id": 1,
      "reward_parcel_amount": 22000,
      "reward_parcel_probability": 5000,
      "is_displayed": true,
      "drop_item_model_prefab_path": "Effect/Common/FX_Common_DropItem_Purple"
    },
    {
      "group_id": 2271403252,
      "reward_parcel_type": 2,
      "reward_parcel_id": 1,
      "reward_parcel_amount": 16350,
      "reward_parcel_probability": 4000,
      "is_displayed": true,
      "drop_item_model_prefab_path": "Effect/Common/FX_Common_DropItem_Blue"
    },
    {
      "group_id": 2934645346,
      "reward_parcel_type": 2,
      "reward_parcel_id": 1,
      "reward_parcel_amount": 35160,
      "reward_parcel_probability": 1000,
      "is_displayed": true,
      "drop_item_model_prefab_path": "Effect/Common/FX_Common_DropItem_Yellow"
    },
    {
      "group_id": 2934645346,
      "reward_parcel_type": 2,
      "reward_parcel_id": 1,
      "reward_parcel_amount": 23680,
      "reward_parcel_probability": 5000,
      "is_displayed": true,
      "drop_item_model_prefab_path": "Effect/Common/FX_Common_DropItem_Purple"
    },
    {
      "group_id": 2934645346,
      "reward_parcel_type": 2,
      "reward_parcel_id": 1,
      "reward_parcel_amount": 17610,
      "reward_parcel_probability": 4000,
      "is_displayed": true,
      "drop_item_model_prefab_path": "Effect/Common/FX_Common_DropItem_Blue"
    },
    {
      "group_id": 1616199885,
      "reward_parcel_type": 2,
      "reward_parcel_id": 1,
      "reward_parcel_amount": 38850,
      "reward_parcel_probability": 1000,
      "is_displayed": true,
      "drop_item_model_prefab_path": "Effect/Common/FX_Common_DropItem_Yellow"
    },
    {
      "group_id": 1616199885,
      "reward_parcel_type": 2,
      "reward_parcel_id": 1,
      "reward_parcel_amount": 26150,
      "reward_parcel_probability": 5000,
      "is_displayed": true,
      "drop_item_model_prefab_path": "Effect/Common/FX_Common_DropItem_Purple"
    },
    {
      "group_id": 1616199885,
      "reward_parcel_type": 2,
      "reward_parcel_id": 1,
      "reward_parcel_amount": 19500,
      "reward_parcel_probability": 4000,
      "is_displayed": true,
      "drop_item_model_prefab_path": "Effect/Common/FX_Common_DropItem_Blue"
    },
    {
      "group_id": 1536500265,
      "reward_parcel_type": 2,
      "reward_parcel_id": 1,
      "reward_parcel_amount": 42720,
      "reward_parcel_probability": 1000,
      "is_displayed": true,
      "drop_item_model_prefab_path": "Effect/Common/FX_Common_DropItem_Yellow"
    },
    {
      "group_id": 1536500265,
      "reward_parcel_type": 2,
      "reward_parcel_id": 1,
      "reward_parcel_amount": 28760,
      "reward_parcel_probability": 5000,
      "is_displayed": true,
      "drop_item_model_prefab_path": "Effect/Common/FX_Common_DropItem_Purple"
    },
    {
      "group_id": 1536500265,
      "reward_parcel_type": 2,
      "reward_parcel_id": 1,
      "reward_parcel_amount": 21460,
      "reward_parcel_probability": 4000,
      "is_displayed": true,
      "drop_item_model_prefab_path": "Effect/Common/FX_Common_DropItem_Blue"
    },
    {
      "group_id": 282876802,
      "reward_parcel_type": 2,
      "reward_parcel_id": 1,
      "reward_parcel_amount": 46440,
      "reward_parcel_probability": 1000,
      "is_displayed": true,
      "drop_item_model_prefab_path": "Effect/Common/FX_Common_DropItem_Yellow"
    },
    {
      "group_id": 282876802,
      "reward_parcel_type": 2,
      "reward_parcel_id": 1,
      "reward_parcel_amount": 31260,
      "reward_parcel_probability": 5000,
      "is_displayed": true,
      "drop_item_model_prefab_path": "Effect/Common/FX_Common_DropItem_Purple"
    },
    {
      "group_id": 282876802,
      "reward_parcel_type": 2,
      "reward_parcel_id": 1,
      "reward_parcel_amount": 23320,
      "reward_parcel_probability": 4000,
      "is_displayed": true,
      "drop_item_model_prefab_path": "Effect/Common/FX_Common_DropItem_Blue"
    },
    {
      "group_id": 2502086614,
      "reward_parcel_type": 2,
      "reward_parcel_id": 1,
      "reward_parcel_amount": 50090,
      "reward_parcel_probability": 1000,
      "is_displayed": true,
      "drop_item_model_prefab_path": "Effect/Common/FX_Common_DropItem_Yellow"
    },
    {
      "group_id": 2502086614,
      "reward_parcel_type": 2,
      "reward_parcel_id": 1,
      "reward_parcel_amount": 33760,
      "reward_parcel_probability": 5000,
      "is_displayed": true,
      "drop_item_model_prefab_path": "Effect/Common/FX_Common_DropItem_Purple"
    },
    {
      "group_id": 2502086614,
      "reward_parcel_type": 2,
      "reward_parcel_id": 1,
      "reward_parcel_amount": 25180,
      "reward_parcel_probability": 4000,
      "is_displayed": true,
      "drop_item_model_prefab_path": "Effect/Common/FX_Common_DropItem_Blue"
    }
  ]
}