{
  "data_list": [
    {
      "event_content_id": 836,
      "dream_maker_schedule_group_id": 100,
      "display_order": 1,
      "localize_etc_id": 1866545121,
      "icon_path": "Dreammaker_Schedule_Icon_01",
      "loading_resource01": "Event_Photo_LoadingImage_836_01_A",
      "loading_resource02": "Event_Photo_LoadingImage_836_01_B",
      "animation_name": "UiAnim_Dreammaker_Progress"
    },
    {
      "event_content_id": 836,
      "dream_maker_schedule_group_id": 200,
      "display_order": 2,
      "localize_etc_id": 205218868,
      "icon_path": "Dreammaker_Schedule_Icon_02",
      "loading_resource01": "Event_Photo_LoadingImage_836_02_A",
      "loading_resource02": "Event_Photo_LoadingImage_836_02_B",
      "animation_name": "UiAnim_Dreammaker_Progress"
    },
    {
      "event_content_id": 836,
      "dream_maker_schedule_group_id": 300,
      "display_order": 3,
      "localize_etc_id": 334263546,
      "icon_path": "Dreammaker_Schedule_Icon_03",
      "loading_resource01": "Event_Photo_LoadingImage_836_03_A",
      "loading_resource02": "Event_Photo_LoadingImage_836_03_B",
      "animation_name": "UiAnim_Dreammaker_Progress"
    },
    {
      "event_content_id": 836,
      "dream_maker_schedule_group_id": 400,
      "display_order": 4,
      "localize_etc_id": 1820452736,
      "icon_path": "Dreammaker_Schedule_Icon_04",
      "loading_resource01": "Event_Photo_LoadingImage_836_04_A",
      "loading_resource02": "Event_Photo_LoadingImage_836_04_B",
      "animation_name": "UiAnim_Dreammaker_Progress"
    }
  ]
}